Metadata-Version: 1.0
Name: smbadi-distributions
Version: 0.1
Summary: Gaussian and Binomial distributions
Home-page: UNKNOWN
Author: Sheila Mbadi
Author-email: mbadidev@gmail.com
License: UNKNOWN
Platform: UNKNOWN
